[
  {
    "nombre": "IPlookup LsVagos",
    "version": "1.0.0",
    "url": "https://www.dropbox.com/scl/fi/etqz8v95h2lhhxiag5fdp/IPLoockup-LsVagos.zip?rlkey=paaloerkqtug7afgvx8o09r07&st=cwqiek1x&dl=1"
  },
  {
    "nombre": "Sniffer",
    "version": "2.0.1",
    "url": "https://www.dropbox.com/scl/fi/o6d9hx1m4klyt0km3l8nb/Sniffer.zip?rlkey=musazd4nhx3phv5i1l8ngd7u6&st=2pfi3g7e&dl=1"
 },
  {
    "nombre": "Pinger LsVagos",
    "version": "1.0.0",
    "url": "https://www.dropbox.com/scl/fi/binsv8o03wb49ced1fpv9/LsVagos-Pinger.zip?rlkey=vv5zv2wsbda55ifeopmbzfofk&st=67ptqj8r&dl=1"
  }
]





